diffa/__init__.py
diffa/diffa.py
diffa-0.0.4.dist-info/LICENSE
diffa-0.0.4.dist-info/METADATA
diffa-0.0.4.dist-info/WHEEL
diffa-0.0.4.dist-info/entry_points.txt
diffa-0.0.4.dist-info/top_level.txt
diffa-0.0.4.dist-info/RECORD
