Metadata-Version: 2.1
Name: diffa
Version: 0.0.4
Summary: A very simple python package for creating a HTML line diff between two files.
Author-email: Tom Carter <tomcarter017@gmail.com>
Maintainer-email: Tom Carter <tomcarter017@gmail.com>
License: MIT License
Project-URL: Homepage, https://github.com/tomcarter23/diffa
Project-URL: Issues, https://github.com/tomcarter23/diffa/issues
Keywords: sample,setuptools,development
Classifier: Development Status :: 3 - Alpha
Classifier: License :: OSI Approved :: MIT License
Classifier: Programming Language :: Python :: 3
Classifier: Programming Language :: Python :: 3.9
Classifier: Programming Language :: Python :: 3.10
Classifier: Programming Language :: Python :: 3.11
Classifier: Programming Language :: Python :: 3.12
Classifier: Programming Language :: Python :: 3.13
Classifier: Programming Language :: Python :: 3 :: Only
Requires-Python: >=3.9
License-File: LICENSE
Requires-Dist: jinja2
Provides-Extra: test
Requires-Dist: pytest; extra == "test"
